rssadd/__init__.py
rssadd/parser.py
rssadd/source_type.py
rssadd-1.1.0.dist-info/LICENSE
rssadd-1.1.0.dist-info/METADATA
rssadd-1.1.0.dist-info/WHEEL
rssadd-1.1.0.dist-info/top_level.txt
rssadd-1.1.0.dist-info/RECORD
